<?xml version="1.0" ?>
<annotation>
<folder>P3人群识别</folder>
<filename>P3_No56.jpg</filename>
<path>C:\Users\sha\OneDrive - njtech.edu.cn\文档\Tencent Files\2397034982\FileRecv\2023年睿抗智能侦察省赛训练数据集\智能侦察数据集\P3人群识别\P3_No56.jpg</path>
<source>
    <database>Unknown</database>
</source>
<size>
    <width>1707</width>
    <height>1280</height>
    <depth>3</depth>
</size>

<segmented>0</segmented>
    <object>
    <name>black</name>
    <pose>Unspecified</pose>
    <truncated>0</truncated>
    <difficult>0</difficult>
    <bndbox>
        <xmin>31</xmin>
        <ymin>451</ymin>
        <xmax>388</xmax>
        <ymax>1053</ymax>
    </bndbox>
</object>
    <object>
    <name>red</name>
    <pose>Unspecified</pose>
    <truncated>0</truncated>
    <difficult>0</difficult>
    <bndbox>
        <xmin>403</xmin>
        <ymin>385</ymin>
        <xmax>613</xmax>
        <ymax>1014</ymax>
    </bndbox>
</object>
    <object>
    <name>blue</name>
    <pose>Unspecified</pose>
    <truncated>0</truncated>
    <difficult>0</difficult>
    <bndbox>
        <xmin>610</xmin>
        <ymin>406</ymin>
        <xmax>826</xmax>
        <ymax>1038</ymax>
    </bndbox>
</object>
    <object>
    <name>black</name>
    <pose>Unspecified</pose>
    <truncated>0</truncated>
    <difficult>0</difficult>
    <bndbox>
        <xmin>823</xmin>
        <ymin>516</ymin>
        <xmax>1080</xmax>
        <ymax>1086</ymax>
    </bndbox>
</object>
    <object>
    <name>black</name>
    <pose>Unspecified</pose>
    <truncated>0</truncated>
    <difficult>0</difficult>
    <bndbox>
        <xmin>1056</xmin>
        <ymin>493</ymin>
        <xmax>1296</xmax>
        <ymax>1083</ymax>
    </bndbox>
</object>
    <object>
    <name>blue</name>
    <pose>Unspecified</pose>
    <truncated>0</truncated>
    <difficult>0</difficult>
    <bndbox>
        <xmin>1286</xmin>
        <ymin>428</ymin>
        <xmax>1685</xmax>
        <ymax>1108</ymax>
    </bndbox>
</object>
</annotation>
