<?xml version="1.0" ?>
<annotation>
<folder>P3人群识别</folder>
<filename>P3_No182.jpg</filename>
<path>C:\Users\sha\OneDrive - njtech.edu.cn\文档\Tencent Files\2397034982\FileRecv\2023年睿抗智能侦察省赛训练数据集\智能侦察数据集\P3人群识别\P3_No182.jpg</path>
<source>
    <database>Unknown</database>
</source>
<size>
    <width>1707</width>
    <height>1280</height>
    <depth>3</depth>
</size>

<segmented>0</segmented>
    <object>
    <name>black</name>
    <pose>Unspecified</pose>
    <truncated>0</truncated>
    <difficult>0</difficult>
    <bndbox>
        <xmin>49</xmin>
        <ymin>651</ymin>
        <xmax>289</xmax>
        <ymax>1155</ymax>
    </bndbox>
</object>
    <object>
    <name>black</name>
    <pose>Unspecified</pose>
    <truncated>0</truncated>
    <difficult>0</difficult>
    <bndbox>
        <xmin>235</xmin>
        <ymin>573</ymin>
        <xmax>541</xmax>
        <ymax>1194</ymax>
    </bndbox>
</object>
    <object>
    <name>red</name>
    <pose>Unspecified</pose>
    <truncated>0</truncated>
    <difficult>0</difficult>
    <bndbox>
        <xmin>526</xmin>
        <ymin>552</ymin>
        <xmax>847</xmax>
        <ymax>1149</ymax>
    </bndbox>
</object>
    <object>
    <name>black</name>
    <pose>Unspecified</pose>
    <truncated>0</truncated>
    <difficult>0</difficult>
    <bndbox>
        <xmin>859</xmin>
        <ymin>567</ymin>
        <xmax>1107</xmax>
        <ymax>1134</ymax>
    </bndbox>
</object>
    <object>
    <name>blue</name>
    <pose>Unspecified</pose>
    <truncated>0</truncated>
    <difficult>0</difficult>
    <bndbox>
        <xmin>1116</xmin>
        <ymin>573</ymin>
        <xmax>1344</xmax>
        <ymax>1155</ymax>
    </bndbox>
</object>
    <object>
    <name>black</name>
    <pose>Unspecified</pose>
    <truncated>0</truncated>
    <difficult>0</difficult>
    <bndbox>
        <xmin>1359</xmin>
        <ymin>546</ymin>
        <xmax>1641</xmax>
        <ymax>1152</ymax>
    </bndbox>
</object>
</annotation>
